mirror_man/__init__.py
mirror_man/cli.py
mirror_man/mirror_data.py
mirror_man/version.py
mirror_man-0.1.2.dist-info/licenses/LICENSE
mirror_man-0.1.2.dist-info/METADATA
mirror_man-0.1.2.dist-info/WHEEL
mirror_man-0.1.2.dist-info/entry_points.txt
mirror_man-0.1.2.dist-info/top_level.txt
mirror_man-0.1.2.dist-info/RECORD
