Metadata-Version: 2.4
Name: mirror-man
Version: 0.1.2
Summary: A CLI tool to manage mirror sources for various Linux distributions.
Author-email: Your Name <your.email@example.com>
License: MIT License
Project-URL: Homepage, https://github.com/hiyongliz/mirror-man
Project-URL: Repository, https://github.com/hiyongliz/mirror-man.git
Classifier: Development Status :: 3 - Alpha
Classifier: Intended Audience :: Developers
Classifier: License :: OSI Approved :: MIT License
Classifier: Programming Language :: Python :: 3
Classifier: Programming Language :: Python :: 3.8
Classifier: Programming Language :: Python :: 3.9
Classifier: Programming Language :: Python :: 3.10
Classifier: Programming Language :: Python :: 3.11
Classifier: Programming Language :: Python :: 3.12
License-File: LICENSE
Requires-Dist: typer>=0.9.0
Dynamic: license-file
